x402_xrpl/README.md
x402_xrpl/__init__.py
x402_xrpl/facilitator.py
x402_xrpl/types.py
x402_xrpl/xrpl_currency.py
x402_xrpl/client/__init__.py
x402_xrpl/client/presigned_payment_payer.py
x402_xrpl/clients/__init__.py
x402_xrpl/clients/base.py
x402_xrpl/clients/py.typed
x402_xrpl/clients/requests.py
x402_xrpl/server/__init__.py
x402_xrpl/server/fastapi.py
x402_xrpl-0.1.4.dist-info/METADATA
x402_xrpl-0.1.4.dist-info/WHEEL
x402_xrpl-0.1.4.dist-info/top_level.txt
x402_xrpl-0.1.4.dist-info/RECORD
