Metadata-Version: 2.4
Name: x402-xrpl
Version: 0.1.4
Summary: XRPL implementation of x402 payments (presigned Payment scheme) with client + FastAPI/Starlette helpers
Author: Facilitator Team
Requires-Python: >=3.11
Requires-Dist: fastapi<0.116,>=0.115
Requires-Dist: uvicorn[standard]<0.31,>=0.30
Requires-Dist: xrpl-py>=4.1.0
Requires-Dist: pydantic<3,>=2
Requires-Dist: python-dotenv<2,>=1
Requires-Dist: requests<3,>=2
Requires-Dist: prometheus-client<0.22,>=0.21
Requires-Dist: redis<6,>=5
Requires-Dist: httpx>=0.28.1
Requires-Dist: cryptography>=45.0.6
Requires-Dist: openai<2,>=1
